AUTHORS
COPYING
MANIFEST.in
README
setup.py
django_pile.egg-info/PKG-INFO
django_pile.egg-info/SOURCES.txt
django_pile.egg-info/dependency_links.txt
django_pile.egg-info/top_level.txt
pile/__init__.py
pile/base.py
pile/fields.py
pile/models.py
pile/queryset.py
pile/search_base.py
pile/views.py
pile/templatetags/__init__.py
pile/templatetags/pile.py