Metadata-Version: 1.0
Name: django-pile
Version: 0.8.1
Summary: A pile of django code for common use over multiple websites.
Home-page: https://github.com/doctormo/django-pile
Author: Martin Owens
Author-email: doctormo@gmail.com
License: AGPLv3
Platform: linux
